py_sr25519_bindings_fork-0.2.4.dist-info/METADATA
py_sr25519_bindings_fork-0.2.4.dist-info/WHEEL
sr25519_nbx/__init__.py
sr25519_nbx/sr25519_nbx.cpython-38-x86_64-linux-gnu.so
py_sr25519_bindings_fork-0.2.4.dist-info/RECORD
