Metadata-Version: 2.1
Name: py-sr25519-bindings-fork
Version: 0.2.4
Classifier: License :: OSI Approved :: Apache Software License
Classifier: Intended Audience :: Developers
Classifier: Programming Language :: Python :: 3
Classifier: Programming Language :: Python :: 3.5
Classifier: Programming Language :: Python :: 3.6
Classifier: Programming Language :: Python :: 3.7
Classifier: Programming Language :: Python :: 3.8
Classifier: Programming Language :: Python :: 3.9
Classifier: Programming Language :: Python :: 3.10
Summary: Fork Python bindings for sr25519 library
Home-Page: https://github.com/aghamir/py-sr25519-bindings
Author: Polkascan Foundation
Maintainer: Mohammad Aghamir
Maintainer-email: 
License: Apache-2.0
Project-URL: Source Code, https://github.com/aghamir/py-sr25519-bindings
